{
    "scene" : {
        "image_index": 592,
        "objects": [
            {
                "color": "yellow",
                "size": "large",
                "rotation": 166.6769740934143,
                "shape": "cylinder",
                "3d_coords": [
                    -2.1402127742767334,
                    -0.8880380392074585,
                    0.699999988079071
                ],
                "material": "metal",
                "pixel_coords": [
                    145,
                    110,
                    11.637372970581055
                ]
            },
            {
                "color": "green",
                "size": "small",
                "rotation": 215.13076541359735,
                "shape": "cube",
                "3d_coords": [
                    0.18743644654750824,
                    -1.3129136562347412,
                    0.3499999940395355
                ],
                "material": "metal",
                "pixel_coords": [
                    196,
                    172,
                    10.09752368927002
                ]
            },
            {
                "color": "gray",
                "size": "small",
                "rotation": 338.8757118843738,
                "shape": "cube",
                "3d_coords": [
                    -1.732337474822998,
                    2.833427667617798,
                    0.3499999940395355
                ],
                "material": "metal",
                "pixel_coords": [
                    276,
                    85,
                    13.70044231414795
                ]
            }
        ],
        "relationships": {
            "right": [
                [
                    1,
                    2
                ],
                [
                    2
                ],
                []
            ],
            "behind": [
                [
                    2
                ],
                [
                    0,
                    2
                ],
                []
            ],
            "front": [
                [
                    1
                ],
                [],
                [
                    0,
                    1
                ]
            ],
            "left": [
                [],
                [
                    0
                ],
                [
                    0,
                    1
                ]
            ]
        },
        "image_filename": "CLEVR_train_000592.png",
        "split": "train",
        "directions": {
            "right": [
                0.6563112735748291,
                0.7544902563095093,
                -0.0
            ],
            "behind": [
                -0.754490315914154,
                0.6563112735748291,
                0.0
            ],
            "above": [
                0.0,
                0.0,
                1.0
            ],
            "below": [
                -0.0,
                -0.0,
                -1.0
            ],
            "left": [
                -0.6563112735748291,
                -0.7544902563095093,
                0.0
            ],
            "front": [
                0.754490315914154,
                -0.6563112735748291,
                -0.0
            ]
        }
    },

    "clause" : [
        {
            "kind" : "select",
            "attribute" : "color",
            "value" : "yellow",
            "variable" : "x"
        }
    ]
}